<?xml version="1.0" encoding="UTF-8"?>
<provinces version="1.2">
<province name="欧洲精选" order="b" >
<city name="俄罗斯" type="1888" order="D" >
	
<video name="俄罗斯 航天员训练室">
<url>http://83.69.197.220/mjpg/video.mjpg?resolution=352x288</url>
</video>

<video name="俄罗斯-莫斯科 高速公路">
<url>http://camera2.butovo.com/mjpg/video.mjpg?resolution=352x288</url>
</video>

<video name="俄罗斯 俱乐部前台4">
<url>http://95.66.143.37:200/mjpg/video.mjpg?resolution=352x288</url>
</video>

<video name="俄罗斯 游戏俱乐部">
<url>http://212.42.54.137:8008/mjpg/video.mjpg?resolution=352x288</url>
</video>

<video name="俄罗斯 托木斯克酒店室内">
<url>http://mfc.tomsk.ru:8080/mjpg/video.mjpg?resolution=352x288</url>
</video>

<video name="俄罗斯 纹身室11">
<url>http://77.239.244.46/mjpg/video.mjpg?resolution=352x288</url>
</video>



<video name="俄罗斯-莫斯科 城市风貌2">
<url>http://camera.butovo.com/mjpg/video.mjpg?resolution=352x288</url>
</video>

<video name="俄罗斯-莫斯科 城市风貌3">
<url>http://94.198.109.177/mjpg/video.mjpg?resolution=352x288</url>
</video>




<video name="俄罗斯 跨海大桥22">
<url>http://77.35.104.40/cgi-bin/faststream.jpg?stream=full::1;fps=5::1;rand=439357::1;quality=60::1;size=320x240</url>
</video>



<video name="俄罗斯 切博克萨雷 高楼下的游乐场">
<url>http://89.151.180.66/mjpg/video.mjpg?resolution=352x288</url>
</video>

<video name="俄罗斯 托木斯克 城市风貌">
<url>http://217.29.93.100/mjpg/video.mjpg?resolution=352x288</url>
</video>

<video name="俄罗斯 斑马线3">
<url>http://webcam.lanta-net.ru/mjpg/video.mjpg?resolution=352x288</url>
</video>

<video name="俄罗斯 Ufa Bashkortostan  酒店前台">
<url>http://92.50.128.90/mjpg/video.mjpg?resolution=352x288</url>
</video>


<video name="俄罗斯 车里雅宾斯克 停车场2">
<url>http://213.110.31.66/mjpg/video.mjpg?resolution=352x288</url>
</video>

<video name="俄罗斯-莫斯科 城市风貌11">
<url>http://217.197.122.134/mjpg/video.mjpg?resolution=352x288</url>
</video>

<video name="俄罗斯 车里雅宾斯克 Satka 停车场3">
<url>http://213.110.31.22/mjpg/video.mjpg?resolution=352x288</url>
</video>

<video name="俄罗斯 雅罗斯拉夫尔 Rostov amarks前台">
<url>http://213.138.74.82:2020/mjpg/video.mjpg?resolution=352x288</url>
</video>

<video name="俄罗斯 游戏俱乐部6">
<url>http://212.42.54.135:8008/mjpg/video.mjpg?resolution=352x288</url>
</video>

<video name="俄罗斯 车里雅宾斯克 Raduzhnyy 城市广场">
<url>http://91.143.62.11/mjpg/video.mjpg?resolution=352x288</url>
</video>

<video name="俄罗斯 克拉斯诺达尔 Sochi 海边浴场">
<url>http://62.182.141.132/mjpg/video.mjpg?resolution=352x288</url>
</video>


<video name="俄罗斯 车里雅宾斯克 Satka 政府大楼4">
<url>http://213.110.31.10/mjpg/video.mjpg?resolution=352x288</url>
</video>


<video name="俄罗斯 车里雅宾斯克 Satka 街边5">
<url>http://213.110.31.26/mjpg/video.mjpg?resolution=352x288</url>
</video>


<video name="俄罗斯-莫斯科 湖边19">
<url>http://camera1.butovo.com/mjpg/video.mjpg?resolution=352x288</url>
</video>


<video name="俄罗斯 圣彼得堡 小区游乐场4">
<url>http://95.161.27.6/mjpg/video.mjpg?resolution=352x288</url>
</video>

<video name="俄罗斯 托木斯克 喷泉广场3">
<url>http://212.192.120.253/mjpg/video.mjpg?resolution=352x288</url>
</video>


<video name="俄罗斯 圣彼得堡 小区游乐场5">
<url>http://95.161.27.60/mjpg/video.mjpg?resolution=352x288</url>
</video>

<video name="俄罗斯 游戏俱乐部14">
<url>http://212.42.54.136:8008/mjpg/video.mjpg?resolution=352x288</url>
</video>


<video name="俄罗斯 城市广场16">
<url>http://195.54.9.138/mjpg/video.mjpg?resolution=352x288</url>
</video>


<video name="Belgorod Belgorod 俄罗斯 amaks前台">
<url>http://94.232.8.10/mjpg/video.mjpg?resolution=352x288</url>
</video>


<video name="Magadan Magadan 俄罗斯 山林小屋2">
<url>http://89.28.252.212/mjpg/video.mjpg?resolution=352x288</url>
</video>

<video name="俄罗斯-莫斯科 城市鸟瞰32">
<url>http://portal.kurkino.net.ru:801/mjpg/video.mjpg?resolution=352x288</url>
</video>

</city>
</province>
</provinces>
